kassandra/__init__.py
kassandra/build_utils.py
kassandra/models.py
kassandra/utils.py
kassandra-0.0.12.dist-info/LICENSE.md
kassandra-0.0.12.dist-info/METADATA
kassandra-0.0.12.dist-info/WHEEL
kassandra-0.0.12.dist-info/top_level.txt
kassandra-0.0.12.dist-info/RECORD
