Metadata-Version: 2.1
Name: kassandra
Version: 0.0.12
Summary: Package for implementing bayesian deep learning models in python.
Home-page: https://github.com/James-Montgomery/kassandra
Author: James Montgomery
Author-email: jamesoneillmontgomery@gmail.com
License: UNKNOWN
Platform: UNKNOWN
Classifier: Programming Language :: Python :: 3
Classifier: License :: OSI Approved :: MIT License
Classifier: Operating System :: OS Independent
Requires-Dist: tensorflow (==1.13.1)
Requires-Dist: tensorflow-probability (==0.6.0)
Requires-Dist: numpy (>=1.15.1)
Requires-Dist: scipy (>=1.1.0)
Requires-Dist: matplotlib (>=2.2.3)
Requires-Dist: seaborn (>=0.9.0)
Requires-Dist: nose (>=1.3.7)
Requires-Dist: coverage (==4.0.0)
Requires-Dist: pylint (>=1.8.2)
